VueJsJiaochengWaiBowang/README.md
VueJsJiaochengWaiBowang/__init__.py
VueJsJiaochengWaiBowang/__main__.py
VueJsJiaochengWaiBowang/file.epub
VueJsJiaochengWaiBowang/index.html
VueJsJiaochengWaiBowang/css/__init__.py
VueJsJiaochengWaiBowang/css/annotations.css
VueJsJiaochengWaiBowang/css/main.css
VueJsJiaochengWaiBowang/css/normalize.css
VueJsJiaochengWaiBowang/css/popup.css
VueJsJiaochengWaiBowang/font/__init__.py
VueJsJiaochengWaiBowang/font/fontello.eot
VueJsJiaochengWaiBowang/font/fontello.svg
VueJsJiaochengWaiBowang/font/fontello.ttf
VueJsJiaochengWaiBowang/font/fontello.woff
VueJsJiaochengWaiBowang/img/__init__.py
VueJsJiaochengWaiBowang/img/annotator-glyph-sprite.png
VueJsJiaochengWaiBowang/img/annotator-icon-sprite.png
VueJsJiaochengWaiBowang/img/apple-touch-icon.png
VueJsJiaochengWaiBowang/img/cancelfullscreen.png
VueJsJiaochengWaiBowang/img/close.png
VueJsJiaochengWaiBowang/img/fullscreen.png
VueJsJiaochengWaiBowang/img/loader.gif
VueJsJiaochengWaiBowang/img/menu-icon.png
VueJsJiaochengWaiBowang/img/save.png
VueJsJiaochengWaiBowang/img/saved.png
VueJsJiaochengWaiBowang/img/settings-s.png
VueJsJiaochengWaiBowang/img/settings.png
VueJsJiaochengWaiBowang/img/star.png
VueJsJiaochengWaiBowang/js/__init__.py
VueJsJiaochengWaiBowang/js/epub.js
VueJsJiaochengWaiBowang/js/epub.min.js
VueJsJiaochengWaiBowang/js/epub.min.map
VueJsJiaochengWaiBowang/js/hooks.min.js
VueJsJiaochengWaiBowang/js/hooks.min.map
VueJsJiaochengWaiBowang/js/reader.js
VueJsJiaochengWaiBowang/js/reader.js.map
VueJsJiaochengWaiBowang/js/reader.min.js
VueJsJiaochengWaiBowang/js/reader.min.map
VueJsJiaochengWaiBowang/js/hooks/__init__.py
VueJsJiaochengWaiBowang/js/hooks/extensions/__init__.py
VueJsJiaochengWaiBowang/js/hooks/extensions/highlight.js
VueJsJiaochengWaiBowang/js/libs/__init__.py
VueJsJiaochengWaiBowang/js/libs/jquery.min.js
VueJsJiaochengWaiBowang/js/libs/localforage.min.js
VueJsJiaochengWaiBowang/js/libs/screenfull.js
VueJsJiaochengWaiBowang/js/libs/screenfull.min.js
vue_js_jiaocheng_wai_bowang-2024.3.4.0.dist-info/METADATA
vue_js_jiaocheng_wai_bowang-2024.3.4.0.dist-info/WHEEL
vue_js_jiaocheng_wai_bowang-2024.3.4.0.dist-info/entry_points.txt
vue_js_jiaocheng_wai_bowang-2024.3.4.0.dist-info/top_level.txt
vue_js_jiaocheng_wai_bowang-2024.3.4.0.dist-info/RECORD
